TrackingNet/Downloader.py
TrackingNet/__init__.py
TrackingNet/utils.py
TrackingNet/data/TEST.json
TrackingNet/data/TRAIN_0.json
TrackingNet/data/TRAIN_1.json
TrackingNet/data/TRAIN_10.json
TrackingNet/data/TRAIN_11.json
TrackingNet/data/TRAIN_2.json
TrackingNet/data/TRAIN_3.json
TrackingNet/data/TRAIN_4.json
TrackingNet/data/TRAIN_5.json
TrackingNet/data/TRAIN_6.json
TrackingNet/data/TRAIN_7.json
TrackingNet/data/TRAIN_8.json
TrackingNet/data/TRAIN_9.json
TrackingNet-0.0.9.dist-info/METADATA
TrackingNet-0.0.9.dist-info/WHEEL
TrackingNet-0.0.9.dist-info/top_level.txt
TrackingNet-0.0.9.dist-info/RECORD
