Metadata-Version: 2.1
Name: TrackingNet
Version: 0.0.9
Summary: TrackingNet SDK
Home-page: https://github.com/SilvioGiancola/TrackingNet
Author: Silvio Giancola
Author-email: silvio.giancola@kaust.edu.sa
License: MIT
Keywords: TrackingNet,SDK,Tracking,Video
Platform: UNKNOWN
Classifier: Development Status :: 3 - Alpha
Classifier: Intended Audience :: Developers
Classifier: Topic :: Software Development :: Build Tools
Classifier: License :: OSI Approved :: MIT License
Classifier: Programming Language :: Python :: 3
Classifier: Programming Language :: Python :: 3.4
Classifier: Programming Language :: Python :: 3.5
Classifier: Programming Language :: Python :: 3.6
Classifier: Programming Language :: Python :: 3.7
Classifier: Programming Language :: Python :: 3.8
Classifier: Programming Language :: Python :: 3.9
Classifier: Programming Language :: Python :: 3.10
Classifier: Programming Language :: Python :: 3.11
Requires-Dist: tqdm
Requires-Dist: scikit-video
Requires-Dist: google-measurement-protocol
Requires-Dist: huggingface-hub
